lumflux/__init__.py
lumflux/_version.py
lumflux/base.py
lumflux/cache.py
lumflux/constructor.py
lumflux/main_controllers.py
lumflux/opts.py
lumflux/pane.py
lumflux/param.py
lumflux/sources.py
lumflux/support.py
lumflux/template.py
lumflux/tools.py
lumflux/transforms.py
lumflux/variables.py
lumflux/views.py
lumflux/widgets.py
tests/__init__.py
tests/test_lumflux.py
lumflux-0.1.0.dist-info/LICENSE
lumflux-0.1.0.dist-info/METADATA
lumflux-0.1.0.dist-info/WHEEL
lumflux-0.1.0.dist-info/top_level.txt
lumflux-0.1.0.dist-info/RECORD
