Metadata-Version: 2.1
Name: lumflux
Version: 0.1.0
Summary: Illuminating web applications.
Home-page: https://github.com/Jhsmit/lumflux
Author: Jochem H. Smit
Author-email: jhsmit@gmail.com
Maintainer: Jochem H. Smit
Maintainer-email: jhsmit@gmail.com
License: MIT
Platform: UNKNOWN
Classifier: Natural Language :: English
Classifier: Development Status :: 2 - Pre-Alpha
Classifier: Programming Language :: Python :: 3.8
Classifier: Programming Language :: Python :: 3.9
Requires-Python: >=3.8
Requires-Dist: holoviews
Requires-Dist: param
Requires-Dist: panel
Requires-Dist: pandas
Requires-Dist: proplot
Requires-Dist: matplotlib
Requires-Dist: numpy
Requires-Dist: pyyaml
Provides-Extra: dev
Requires-Dist: bandit ; extra == 'dev'
Requires-Dist: black ; extra == 'dev'
Requires-Dist: invoke ; extra == 'dev'
Requires-Dist: mypy ; extra == 'dev'
Requires-Dist: pylint ; extra == 'dev'
Requires-Dist: pytest ; extra == 'dev'
Requires-Dist: flake8 ; extra == 'dev'
Provides-Extra: docs
Requires-Dist: sphinx (>=4.4.0) ; extra == 'docs'
Requires-Dist: ipykernel ; extra == 'docs'
Requires-Dist: nbsphinx ; extra == 'docs'
Requires-Dist: furo ; extra == 'docs'
Requires-Dist: sphinx-copybutton ; extra == 'docs'
Requires-Dist: sphinx-autodoc-typehints ; extra == 'docs'
Requires-Dist: sphinx-autobuild ; extra == 'docs'
Requires-Dist: sphinxcontrib-bibtex ; extra == 'docs'
